{
    "UE": "NO",
    "changeDate": "2025-04-16T09:12:22",
    "description": "projekt dotyczy ratyfikacji Umowy, której zakresem przedmiotowym (art. 2) po Stronie polskiej zostaną objęte takie świadczenia jak: emerytury, renty z tytułu niezdolności do pracy, renty rodzinne, jednorazowe odszkodowania oraz renty z tytułu wypadków przy pracy i chorób zawodowych oraz zasiłki pogrzebowe. Umowa będzie miała również zastosowanie do ustawodawstwa dotyczącego obowiązkowego ubezpieczenia. Zakres przedmiotowy Umowy po Stronie indyjskiej obejmuje przewidziane ustawodawstwem indyjskim emerytury i renty rodzinne dla osób zatrudnionych oraz renty z tytułu trwalej niezdolności do pracy dla osób zatrudnionych",
    "documentDate": "2025-04-09",
    "documentType": "projekt ustawy",
    "documentTypeEnum": "BILL",
    "legislativeCommittee": false,
    "links": [],
    "number": "1173",
    "passed": false,
    "principleOfSubsidiarity": false,
    "processStartDate": "2025-04-09",
    "shortenProcedure": false,
    "stages": [
        {
            "date": "2025-04-09",
            "stageName": "Projekt wpłynął do Sejmu",
            "printNumber": "1173",
            "stageType": "Start"
        },
        {
            "children": [
                {
                    "date": "2025-04-16",
                    "stageName": "Skierowanie",
                    "committeeCode": "SZA",
                    "stageType": "Referral",
                    "type": "NORMAL"
                },
                {
                    "date": "2025-04-16",
                    "stageName": "Skierowanie",
                    "committeeCode": "PSR",
                    "stageType": "Referral",
                    "type": "NORMAL"
                }
            ],
            "date": "2025-04-16",
            "stageName": "Skierowano do I czytania w komisjach",
            "stageType": "ReadingReferral"
        }
    ],
    "term": 10,
    "title": "Rządowy projekt ustawy o ratyfikacji Umowy między Rzecząpospolitą Polską a Republiką Indii o zabezpieczeniu społecznym, podpisanej w Warszawie dnia 25 listopada 2024 r.",
    "urgencyStatus": "NORMAL",
    "webGeneratedDate": "2025-04-16T09:12:51"
}