{
    "ELI": "DU/2025/1872",
    "UE": "NO",
    "address": "WDU20250001872",
    "changeDate": "2026-01-02T12:43:20",
    "closureDate": "2025-12-04",
    "description": "projekt dotyczy wprowadzenia kar dla osób, które biorą udział w nielegalnych wyścigach czy rajdach, odbywających się na drogach oraz podwyższenia kar za brawurową jazdę",
    "displayAddress": "Dz.U. 2025 poz. 1872",
    "documentDate": "2025-07-03",
    "documentType": "projekt ustawy",
    "documentTypeEnum": "BILL",
    "legislativeCommittee": false,
    "links": [
        {
            "href": "https://isap.sejm.gov.pl/isap.nsf/DocDetails.xsp?id=WDU20250001872",
            "rel": "isap"
        },
        {
            "href": "https://eli.gov.pl/eli/DU/2025/1872/ogl",
            "rel": "eli"
        },
        {
            "href": "https://api.sejm.gov.pl/eli/acts/DU/2025/1872",
            "rel": "eli-api"
        }
    ],
    "number": "1451",
    "passed": true,
    "principleOfSubsidiarity": false,
    "processStartDate": "2025-07-03",
    "rclLink": "https://legislacja.rcl.gov.pl/getIdFromLegislacja?number=RM-0610-105-25",
    "rclNum": "RM-0610-105-25",
    "shortenProcedure": false,
    "stages": [
        {
            "date": "2025-07-03",
            "stageName": "Projekt wpłynął do Sejmu",
            "printNumber": "1451",
            "stageType": "Start"
        },
        {
            "children": [
                {
                    "date": "2025-07-07",
                    "stageName": "Skierowanie",
                    "committeeCode": "Sejm",
                    "stageType": "Referral",
                    "type": "NORMAL"
                }
            ],
            "date": "2025-07-07",
            "stageName": "Skierowano do I czytania na posiedzeniu Sejmu",
            "stageType": "ReadingReferral"
        },
        {
            "children": [
                {
                    "date": "2025-07-22",
                    "stageName": "Skierowanie",
                    "committeeCode": "NKK",
                    "stageType": "Referral",
                    "type": "NORMAL"
                }
            ],
            "date": "2025-07-22",
            "stageName": "I czytanie na posiedzeniu Sejmu",
            "sittingNum": 39,
            "stageType": "SejmReading"
        },
        {
            "children": [
                {
                    "date": "2025-10-06",
                    "stageName": "Sprawozdanie podkomisji",
                    "minorityMotions": 0,
                    "reportFile": "https://api.sejm.gov.pl/sejm/term10/processes/1451/attachment/spr_1451.pdf",
                    "stageType": "CommitteeReport",
                    "subCommittee": true
                },
                {
                    "date": "2025-10-15",
                    "stageName": "Sprawozdanie komisji",
                    "minorityMotions": 0,
                    "printNumber": "1822",
                    "proposal": "załączony projekt ustawy",
                    "rapporteurID": "491",
                    "rapporteurName": "Aleksandra Kot",
                    "reportFile": "https://api.sejm.gov.pl/sejm/term10/prints/1822/1822.pdf",
                    "stageType": "CommitteeReport",
                    "subCommittee": false
                }
            ],
            "date": "2025-10-06",
            "stageName": "Praca w komisjach po I czytaniu",
            "stageType": "CommitteeWork"
        },
        {
            "children": [
                {
                    "date": "2025-11-06",
                    "stageName": "Skierowanie",
                    "committeeCode": "NKK",
                    "stageType": "Referral",
                    "type": "NORMAL"
                }
            ],
            "date": "2025-11-06",
            "stageName": "II czytanie na posiedzeniu Sejmu",
            "comment": "poprawki",
            "decision": "skierowano ponownie do komisji w celu przedstawienia sprawozdania",
            "sittingNum": 44,
            "stageType": "SejmReading"
        },
        {
            "children": [
                {
                    "date": "2025-11-07",
                    "stageName": "Sprawozdanie komisji",
                    "minorityMotions": 0,
                    "printNumber": "1822-A",
                    "proposal": "przyjąć część poprawek",
                    "rapporteurID": "491",
                    "rapporteurName": "Aleksandra Kot",
                    "reportFile": "https://api.sejm.gov.pl/sejm/term10/prints/1822-A/1822-A.pdf",
                    "stageType": "CommitteeReport",
                    "subCommittee": false
                }
            ],
            "date": "2025-11-07",
            "stageName": "Praca w komisjach po II czytaniu",
            "stageType": "CommitteeWork"
        },
        {
            "children": [
                {
                    "date": "2025-11-07",
                    "stageName": "Głosowanie",
                    "stageType": "Voting",
                    "voting": {
                        "abstain": 23,
                        "date": "2025-11-07T18:28:24",
                        "description": "całość projektu ustawy",
                        "kind": "ELECTRONIC",
                        "links": [
                            {
                                "href": "https://api.sejm.gov.pl/sejm/term10/votings/44/84/pdf",
                                "rel": "pdf"
                            }
                        ],
                        "majorityType": "SIMPLE_MAJORITY",
                        "majorityVotes": 175,
                        "no": 174,
                        "notParticipating": 16,
                        "present": 0,
                        "sitting": 44,
                        "sittingDay": 3,
                        "term": 10,
                        "title": "Pkt. 29 Sprawozdanie Komisji o rządowym projekcie ustawy o zmianie niektórych ustaw w celu poprawy bezpieczeństwa ruchu drogowego (druki nr 1451, 1822 i 1822-A)",
                        "topic": "głosowanie nad całością projektu.",
                        "totalVoted": 444,
                        "votingNumber": 84,
                        "yes": 247
                    }
                }
            ],
            "date": "2025-11-07",
            "stageName": "III czytanie na posiedzeniu Sejmu",
            "comment": "poprawki",
            "decision": "uchwalono",
            "sittingNum": 44,
            "stageType": "SejmReading",
            "textAfter3": "https://api.sejm.gov.pl/sejm/term10/processes/1451/attachment/1451_u3.pdf"
        },
        {
            "children": [
                {
                    "date": "2025-11-28",
                    "stageName": "Skierowanie",
                    "committeeCode": "NKK",
                    "stageType": "Referral",
                    "type": "NORMAL"
                }
            ],
            "date": "2025-11-27",
            "stageName": "Stanowisko Senatu",
            "position": "wniósł poprawki",
            "printNumber": "2019",
            "stageType": "SenatePosition"
        },
        {
            "children": [
                {
                    "date": "2025-12-04",
                    "stageName": "Sprawozdanie komisji",
                    "minorityMotions": 0,
                    "printNumber": "2043",
                    "proposal": "przyjąć poprawki",
                    "rapporteurID": "491",
                    "rapporteurName": "Aleksandra Kot",
                    "reportFile": "https://api.sejm.gov.pl/sejm/term10/prints/2043/2043.pdf",
                    "stageType": "CommitteeReport",
                    "subCommittee": false
                }
            ],
            "date": "2025-12-04",
            "stageName": "Praca w komisjach nad stanowiskiem Senatu",
            "stageType": "CommitteeWork"
        },
        {
            "date": "2025-12-04",
            "stageName": "Rozpatrywanie na forum Sejmu stanowiska Senatu",
            "decision": "przyjęto poprawki",
            "sittingNum": 46,
            "stageType": "SenatePositionConsideration"
        },
        {
            "date": "2025-12-05",
            "stageName": "Ustawę przekazano Prezydentowi do podpisu",
            "stageType": "ToPresident"
        },
        {
            "date": "2025-12-22",
            "stageName": "Prezydent podpisał ustawę",
            "omittedInconsistent": false,
            "stageType": "PresidentSignature"
        },
        {
            "stageName": "Uchwalono",
            "stageType": "End"
        }
    ],
    "term": 10,
    "title": "Rządowy projekt ustawy o zmianie niektórych ustaw w celu poprawy bezpieczeństwa ruchu drogowego",
    "titleFinal": "o zmianie niektórych ustaw w celu poprawy bezpieczeństwa ruchu drogowego",
    "urgencyStatus": "NORMAL",
    "webGeneratedDate": "2026-01-07T08:26:26"
}