{
    "ELI": "DU/2024/928",
    "UE": "ENFORCEMENT",
    "address": "WDU20240000928",
    "changeDate": "2024-06-27T19:38:13",
    "closureDate": "2024-06-14",
    "description": "projekt dotyczy wdrożenia dyrektywy Parlamentu Europejskiego i Rady, której celem jest poprawa egzekwowania prawa i polityk UE w określonych dziedzinach przez ustanowienie wspólnych minimalnych norm zapewniających odpowiedni poziom ochrony osób zgłaszających naruszenie prawa UE",
    "displayAddress": "Dz.U. 2024 poz. 928",
    "documentDate": "2024-04-17",
    "documentType": "projekt ustawy",
    "documentTypeEnum": "BILL",
    "legislativeCommittee": false,
    "links": [
        {
            "href": "https://isap.sejm.gov.pl/isap.nsf/DocDetails.xsp?id=WDU20240000928",
            "rel": "isap"
        },
        {
            "href": "https://eli.gov.pl/eli/DU/2024/928/ogl",
            "rel": "eli"
        },
        {
            "href": "https://api.sejm.gov.pl/eli/acts/DU/2024/928",
            "rel": "eli-api"
        }
    ],
    "number": "317",
    "passed": true,
    "principleOfSubsidiarity": false,
    "processStartDate": "2024-04-17",
    "rclLink": "https://legislacja.rcl.gov.pl/getIdFromLegislacja?number=RM-0610-24-24",
    "rclNum": "RM-0610-24-24",
    "shortenProcedure": false,
    "stages": [
        {
            "date": "2024-04-17",
            "stageName": "Projekt wpłynął do Sejmu",
            "printNumber": "317",
            "stageType": "Start"
        },
        {
            "children": [
                {
                    "date": "2024-04-24",
                    "stageName": "Skierowanie",
                    "committeeCode": "PSR",
                    "remarks": "Prolongata do dnia 24-05-2024",
                    "reportDate": "2024-05-20",
                    "stageType": "Referral",
                    "type": "NORMAL"
                }
            ],
            "date": "2024-04-24",
            "stageName": "Skierowano do I czytania w komisjach",
            "stageType": "ReadingReferral"
        },
        {
            "date": "2024-05-08",
            "stageName": "I czytanie w komisjach",
            "stageType": "Reading"
        },
        {
            "children": [
                {
                    "date": "2024-05-21",
                    "stageName": "Sprawozdanie komisji",
                    "minorityMotions": 2,
                    "printNumber": "381",
                    "proposal": "załączony projekt ustawy",
                    "rapporteurID": "402",
                    "rapporteurName": "Katarzyna Ueberhan",
                    "reportFile": "https://api.sejm.gov.pl/sejm/term10/prints/381/381.pdf",
                    "stageType": "CommitteeReport",
                    "subCommittee": false
                }
            ],
            "date": "2024-05-21",
            "stageName": "Praca w komisjach po I czytaniu",
            "stageType": "CommitteeWork"
        },
        {
            "children": [
                {
                    "date": "2024-05-23",
                    "stageName": "Skierowanie",
                    "committeeCode": "PSR",
                    "stageType": "Referral",
                    "type": "NORMAL"
                }
            ],
            "date": "2024-05-22",
            "stageName": "II czytanie na posiedzeniu Sejmu",
            "comment": "wniosek o odrzucenie, poprawki",
            "decision": "skierowano ponownie do komisji w celu przedstawienia sprawozdania",
            "sittingNum": 12,
            "stageType": "SejmReading"
        },
        {
            "children": [
                {
                    "date": "2024-05-23",
                    "stageName": "Sprawozdanie komisji",
                    "minorityMotions": 0,
                    "printNumber": "381-A",
                    "proposal": "przyjąć część poprawek",
                    "rapporteurID": "402",
                    "rapporteurName": "Katarzyna Ueberhan",
                    "reportFile": "https://api.sejm.gov.pl/sejm/term10/prints/381-A/381-A.pdf",
                    "stageType": "CommitteeReport",
                    "subCommittee": false
                }
            ],
            "date": "2024-05-23",
            "stageName": "Praca w komisjach po II czytaniu",
            "stageType": "CommitteeWork"
        },
        {
            "children": [
                {
                    "date": "2024-05-23",
                    "stageName": "Głosowanie",
                    "stageType": "Voting",
                    "voting": {
                        "abstain": 2,
                        "date": "2024-05-23T13:57:38",
                        "description": "całość projektu ustawy",
                        "kind": "ELECTRONIC",
                        "links": [
                            {
                                "href": "https://api.sejm.gov.pl/sejm/term10/votings/12/24/pdf",
                                "rel": "pdf"
                            }
                        ],
                        "majorityType": "SIMPLE_MAJORITY",
                        "majorityVotes": 192,
                        "no": 191,
                        "notParticipating": 31,
                        "present": 0,
                        "sitting": 12,
                        "sittingDay": 2,
                        "term": 10,
                        "title": "Pkt. 4 Sprawozdanie Komisji o rządowym projekcie ustawy o ochronie sygnalistów (druki nr 317, 381 i 381-A)",
                        "topic": "głosowanie nad całością projektu",
                        "totalVoted": 428,
                        "votingNumber": 24,
                        "yes": 235
                    }
                }
            ],
            "date": "2024-05-23",
            "stageName": "III czytanie na posiedzeniu Sejmu",
            "comment": "wniosek o odrzucenie, wnioski mniejszości, poprawki",
            "decision": "uchwalono",
            "sittingNum": 12,
            "stageType": "SejmReading",
            "textAfter3": "https://api.sejm.gov.pl/sejm/term10/processes/317/attachment/317_u3.pdf"
        },
        {
            "children": [
                {
                    "date": "2024-06-05",
                    "stageName": "Skierowanie",
                    "committeeCode": "PSR",
                    "stageType": "Referral",
                    "type": "NORMAL"
                }
            ],
            "date": "2024-06-05",
            "stageName": "Stanowisko Senatu",
            "position": "wniósł poprawki",
            "printNumber": "427",
            "stageType": "SenatePosition"
        },
        {
            "children": [
                {
                    "date": "2024-06-12",
                    "stageName": "Sprawozdanie komisji",
                    "minorityMotions": 0,
                    "printNumber": "455",
                    "proposal": "przyjąć poprawki",
                    "rapporteurID": "402",
                    "rapporteurName": "Katarzyna Ueberhan",
                    "reportFile": "https://api.sejm.gov.pl/sejm/term10/prints/455/455.pdf",
                    "stageType": "CommitteeReport",
                    "subCommittee": false
                }
            ],
            "date": "2024-06-12",
            "stageName": "Praca w komisjach nad stanowiskiem Senatu",
            "stageType": "CommitteeWork"
        },
        {
            "date": "2024-06-14",
            "stageName": "Rozpatrywanie na forum Sejmu stanowiska Senatu",
            "decision": "przyjęto poprawki",
            "sittingNum": 13,
            "stageType": "SenatePositionConsideration"
        },
        {
            "date": "2024-06-17",
            "stageName": "Ustawę przekazano Prezydentowi do podpisu",
            "stageType": "ToPresident"
        },
        {
            "date": "2024-06-19",
            "stageName": "Prezydent podpisał ustawę",
            "omittedInconsistent": false,
            "stageType": "PresidentSignature"
        },
        {
            "stageName": "Uchwalono",
            "stageType": "End"
        }
    ],
    "term": 10,
    "title": "Rządowy projekt ustawy o ochronie sygnalistów",
    "titleFinal": "o ochronie sygnalistów",
    "urgencyStatus": "NORMAL",
    "webGeneratedDate": "2024-07-01T07:52:19"
}