{
  "lastModified": "2024-03-13T14:56:35",
  "links": [
    {
      "href": "https://sejm.gov.pl/sejm10.nsf/interpelacja.xsp?typ=int&nr=1631",
      "rel": "web-description"
    },
    {
      "href": "https://sejm.gov.pl/sejm10.nsf/interpelacjaTresc.xsp?key=D2NGY8",
      "rel": "web-body"
    },
    {
      "href": "https://api.sejm.gov.pl/sejm/term10/interpellations/1631/body",
      "rel": "body"
    }
  ],
  "num": 1631,
  "receiptDate": "2024-02-19",
  "term": 10,
  "title": "Interpelacja w sprawie wycofania skarg złożonych do TSUE na niektóre rozwiązania w unijnym pakiecie klimatycznym \"Fit for 55\"",
  "answerDelayedDays": 0,
  "from": [
    "032",
    "254",
    "399"
  ],
  "recipientDetails": [
    {
      "answerDelayedDays": 0,
      "name": "minister ds. Unii Europejskiej",
      "sent": "2024-02-21"
    }
  ],
  "replies": [
    {
      "from": "Minister Adam Szłapka",
      "key": "D34L9D",
      "lastModified": "2024-03-13T14:56:35",
      "links": [
        {
          "href": "https://sejm.gov.pl/sejm10.nsf/interpelacjaTresc.xsp?key=D34L9D",
          "rel": "web-body"
        },
        {
          "href": "https://api.sejm.gov.pl/sejm/term10/interpellations/1631/reply/D34L9D/body",
          "rel": "body"
        }
      ],
      "onlyAttachment": false,
      "prolongation": false,
      "receiptDate": "2024-03-05"
    }
  ],
  "sentDate": "2024-02-21",
  "to": [
    "minister ds. Unii Europejskiej"
  ]
}