{
  "lastModified": "2024-09-16T22:00:26",
  "links": [
    {
      "href": "https://sejm.gov.pl/sejm10.nsf/interpelacja.xsp?typ=int&nr=3542",
      "rel": "web-description"
    },
    {
      "href": "https://sejm.gov.pl/sejm10.nsf/interpelacjaTresc.xsp?key=D6SAJS",
      "rel": "web-body"
    },
    {
      "href": "https://api.sejm.gov.pl/sejm/term10/interpellations/3542/body",
      "rel": "body"
    }
  ],
  "num": 3542,
  "receiptDate": "2024-06-26",
  "term": 10,
  "title": "Interpelacja w sprawie czasu pracy maszynistów",
  "answerDelayedDays": 0,
  "from": [
    "239"
  ],
  "recipientDetails": [
    {
      "answerDelayedDays": 0,
      "name": "minister infrastruktury",
      "sent": "2024-07-01"
    }
  ],
  "replies": [
    {
      "attachments": [
        {
          "URL": "https://api.sejm.gov.pl/sejm/term10/interpellations/attachment/ATTD96HYF/i03542-o1.pdf",
          "lastModified": "2024-09-16T22:00:26",
          "name": "i03542-o1.pdf"
        }
      ],
      "from": "Podsekretarz stanu Piotr Malepszak",
      "key": "D96HYF",
      "lastModified": "2024-09-16T22:00:26",
      "links": [
        {
          "href": "https://sejm.gov.pl/sejm10.nsf/interpelacjaTresc.xsp?key=D96HYF",
          "rel": "web-body"
        },
        {
          "href": "https://api.sejm.gov.pl/sejm/term10/interpellations/3542/reply/D96HYF/body",
          "rel": "body"
        }
      ],
      "onlyAttachment": true,
      "prolongation": false,
      "receiptDate": "2024-09-13"
    },
    {
      "from": "podsekretarz stanu w Ministerstwie Infrastruktury - Piotr Malepszak",
      "lastModified": "2024-07-29T00:00:00",
      "links": [],
      "onlyAttachment": false,
      "prolongation": true,
      "receiptDate": "2024-07-29"
    },
    {
      "from": "podsekretarz stanu w Ministerstwie Infrastruktury - Piotr Malepszak",
      "lastModified": "2024-08-19T00:00:00",
      "links": [],
      "onlyAttachment": false,
      "prolongation": true,
      "receiptDate": "2024-08-19"
    }
  ],
  "sentDate": "2024-07-01",
  "to": [
    "minister infrastruktury"
  ]
}